[
    { "value": "Home", "tag": "a", "subMenu": null, "href": "/" },
    {
        "value": "Man",
        "tag": "a",
        "subMenu": [
            [
                { "value": "women", "tag": "h3", "subMenu": null, "href": "/catalog/women" },
                { "value": "Dresses", "tag": "a", "subMenu": null, "href": "/catalog/women" },
                { "value": "Tops", "tag": "a", "subMenu": null, "href": "/catalog/women" },
                { "value": "Sweaters/Knits", "tag": "a", "subMenu": null, "href": "/catalog/women" },
                { "value": "Jackets/Coats", "tag": "a", "subMenu": null, "href": "/catalog/women" },
                { "value": "Blazers", "tag": "a", "subMenu": null, "href": "/catalog/women" },
                { "value": "Denim", "tag": "a", "subMenu": null, "href": "/catalog/women" },
                { "value": "Leggings/Pants", "tag": "a", "subMenu": null, "href": "/catalog/women" },
                { "value": "Skirts/Shorts", "tag": "a", "subMenu": null, "href": "/catalog/women" },
                { "value": "Accessories", "tag": "a", "subMenu": null, "href": "/catalog/women" }
            ],
            [
                { "value": "women", "tag": "h3", "subMenu": null, "href": "/catalog/women" },
                { "value": "Dresses", "tag": "a", "subMenu": null, "href": "/catalog/women" },
                { "value": "Tops", "tag": "a", "subMenu": null, "href": "/catalog/women" },
                { "value": "Sweaters/Knits", "tag": "a", "subMenu": null, "href": "/catalog/women" },
                { "value": "Jackets/Coats", "tag": "a", "subMenu": null, "href": "/catalog/women" },
                { "value": "women", "tag": "h3", "subMenu": null, "href": "/catalog/women" },
                { "value": "Dresses", "tag": "a", "subMenu": null, "href": "/catalog/women" },
                { "value": "Tops", "tag": "a", "subMenu": null, "href": "/catalog/women" },
                { "value": "Sweaters/Knits", "tag": "a", "subMenu": null, "href": "/catalog/women" }
            ],
            [
                { "value": "women", "tag": "h3", "subMenu": null, "href": "/catalog/women" },
                { "value": "Dresses", "tag": "a", "subMenu": null, "href": "/catalog/women" },
                { "value": "Tops", "tag": "a", "subMenu": null, "href": "/catalog/women" },
                { "value": "Sweaters/Knits", "tag": "a", "subMenu": null, "href": "/catalog/women" },
                { "value": "Jackets/Coats", "tag": "a", "subMenu": null, "href": "/catalog/women" },
                { "value": "Super <br> sale!", "tag": "div", "subMenu": null, "href": "#" }
            ]
        ],
        "href": "/catalog/man"
    },
    {
        "value": "Women",
        "tag": "a",
        "subMenu": [
            [
                { "value": "women", "tag": "h3", "subMenu": null, "href": "/catalog/women" },
                { "value": "Dresses", "tag": "a", "subMenu": null, "href": "/catalog/women" },
                { "value": "Tops", "tag": "a", "subMenu": null, "href": "/catalog/women" },
                { "value": "Sweaters/Knits", "tag": "a", "subMenu": null, "href": "/catalog/women" },
                { "value": "Jackets/Coats", "tag": "a", "subMenu": null, "href": "/catalog/women" },
                { "value": "Blazers", "tag": "a", "subMenu": null, "href": "/catalog/women" },
                { "value": "Denim", "tag": "a", "subMenu": null, "href": "/catalog/women" },
                { "value": "Leggings/Pants", "tag": "a", "subMenu": null, "href": "/catalog/women" },
                { "value": "Skirts/Shorts", "tag": "a", "subMenu": null, "href": "/catalog/women" },
                { "value": "Accessories", "tag": "a", "subMenu": null, "href": "/catalog/women" }
            ],
            [
                { "value": "women", "tag": "h3", "subMenu": null, "href": "/catalog/women" },
                { "value": "Dresses", "tag": "a", "subMenu": null, "href": "/catalog/women" },
                { "value": "Tops", "tag": "a", "subMenu": null, "href": "/catalog/women" },
                { "value": "Sweaters/Knits", "tag": "a", "subMenu": null, "href": "/catalog/women" },
                { "value": "Jackets/Coats", "tag": "a", "subMenu": null, "href": "/catalog/women" },
                { "value": "women", "tag": "h3", "subMenu": null, "href": "/catalog/women" },
                { "value": "Dresses", "tag": "a", "subMenu": null, "href": "/catalog/women" },
                { "value": "Tops", "tag": "a", "subMenu": null, "href": "/catalog/women" },
                { "value": "Sweaters/Knits", "tag": "a", "subMenu": null, "href": "/catalog/women" }
            ],
            [
                { "value": "women", "tag": "h3", "subMenu": null, "href": "/catalog/women" },
                { "value": "Dresses", "tag": "a", "subMenu": null, "href": "/catalog/women" },
                { "value": "Tops", "tag": "a", "subMenu": null, "href": "/catalog/women" },
                { "value": "Sweaters/Knits", "tag": "a", "subMenu": null, "href": "/catalog/women" },
                { "value": "Jackets/Coats", "tag": "a", "subMenu": null, "href": "/catalog/women" },
                { "value": "Super <br> sale!", "tag": "div", "subMenu": null, "href": "#" }
            ]
        ],
        "href": "/catalog/women"
    },
    {
        "value": "Kids",
        "tag": "a",
        "subMenu": [
            [
                { "value": "women", "tag": "h3", "subMenu": null, "href": "/catalog/women" },
                { "value": "Dresses", "tag": "a", "subMenu": null, "href": "/catalog/women" },
                { "value": "Tops", "tag": "a", "subMenu": null, "href": "/catalog/women" },
                { "value": "Sweaters/Knits", "tag": "a", "subMenu": null, "href": "/catalog/women" },
                { "value": "Jackets/Coats", "tag": "a", "subMenu": null, "href": "/catalog/women" },
                { "value": "Blazers", "tag": "a", "subMenu": null, "href": "/catalog/women" },
                { "value": "Denim", "tag": "a", "subMenu": null, "href": "/catalog/women" },
                { "value": "Leggings/Pants", "tag": "a", "subMenu": null, "href": "/catalog/women" },
                { "value": "Skirts/Shorts", "tag": "a", "subMenu": null, "href": "/catalog/women" },
                { "value": "Accessories", "tag": "a", "subMenu": null, "href": "/catalog/women" }
            ],
            [
                { "value": "women", "tag": "h3", "subMenu": null, "href": "/catalog/women" },
                { "value": "Dresses", "tag": "a", "subMenu": null, "href": "/catalog/women" },
                { "value": "Tops", "tag": "a", "subMenu": null, "href": "/catalog/women" },
                { "value": "Sweaters/Knits", "tag": "a", "subMenu": null, "href": "/catalog/women" },
                { "value": "Jackets/Coats", "tag": "a", "subMenu": null, "href": "/catalog/women" },
                { "value": "women", "tag": "h3", "subMenu": null, "href": "/catalog/women" },
                { "value": "Dresses", "tag": "a", "subMenu": null, "href": "/catalog/women" },
                { "value": "Tops", "tag": "a", "subMenu": null, "href": "/catalog/women" },
                { "value": "Sweaters/Knits", "tag": "a", "subMenu": null, "href": "/catalog/women" }
            ],
            [
                { "value": "women", "tag": "h3", "subMenu": null, "href": "/catalog/women" },
                { "value": "Dresses", "tag": "a", "subMenu": null, "href": "/catalog/women" },
                { "value": "Tops", "tag": "a", "subMenu": null, "href": "/catalog/women" },
                { "value": "Sweaters/Knits", "tag": "a", "subMenu": null, "href": "/catalog/women" },
                { "value": "Jackets/Coats", "tag": "a", "subMenu": null, "href": "/catalog/women" },
                { "value": "Super <br> sale!", "tag": "div", "subMenu": null, "href": "#" }
            ]
        ],
        "href": "/catalog/kids"
    },
    {
        "value": "Accessories",
        "tag": "a",
        "subMenu": [
            [
                { "value": "women", "tag": "h3", "subMenu": null, "href": "/catalog/women" },
                { "value": "Dresses", "tag": "a", "subMenu": null, "href": "/catalog/women" },
                { "value": "Tops", "tag": "a", "subMenu": null, "href": "/catalog/women" },
                { "value": "Sweaters/Knits", "tag": "a", "subMenu": null, "href": "/catalog/women" },
                { "value": "Jackets/Coats", "tag": "a", "subMenu": null, "href": "/catalog/women" },
                { "value": "Blazers", "tag": "a", "subMenu": null, "href": "/catalog/women" },
                { "value": "Denim", "tag": "a", "subMenu": null, "href": "/catalog/women" },
                { "value": "Leggings/Pants", "tag": "a", "subMenu": null, "href": "/catalog/women" },
                { "value": "Skirts/Shorts", "tag": "a", "subMenu": null, "href": "/catalog/women" },
                { "value": "Accessories", "tag": "a", "subMenu": null, "href": "/catalog/women" }
            ],
            [
                { "value": "women", "tag": "h3", "subMenu": null, "href": "/catalog/women" },
                { "value": "Dresses", "tag": "a", "subMenu": null, "href": "/catalog/women" },
                { "value": "Tops", "tag": "a", "subMenu": null, "href": "/catalog/women" },
                { "value": "Sweaters/Knits", "tag": "a", "subMenu": null, "href": "/catalog/women" },
                { "value": "Jackets/Coats", "tag": "a", "subMenu": null, "href": "/catalog/women" },
                { "value": "women", "tag": "h3", "subMenu": null, "href": "/catalog/women" },
                { "value": "Dresses", "tag": "a", "subMenu": null, "href": "/catalog/women" },
                { "value": "Tops", "tag": "a", "subMenu": null, "href": "/catalog/women" },
                { "value": "Sweaters/Knits", "tag": "a", "subMenu": null, "href": "/catalog/women" }
            ],
            [
                { "value": "women", "tag": "h3", "subMenu": null, "href": "/catalog/women" },
                { "value": "Dresses", "tag": "a", "subMenu": null, "href": "/catalog/women" },
                { "value": "Tops", "tag": "a", "subMenu": null, "href": "/catalog/women" },
                { "value": "Sweaters/Knits", "tag": "a", "subMenu": null, "href": "/catalog/women" },
                { "value": "Jackets/Coats", "tag": "a", "subMenu": null, "href": "/catalog/women" },
                { "value": "Super <br> sale!", "tag": "div", "subMenu": null, "href": "#" }
            ]
        ],
        "href": "/catalog/accessories"
    },
    {
        "value": "Featured",
        "tag": "a",
        "subMenu": [
            [
                { "value": "women", "tag": "h3", "subMenu": null, "href": "/catalog/women" },
                { "value": "Dresses", "tag": "a", "subMenu": null, "href": "/catalog/women" },
                { "value": "Tops", "tag": "a", "subMenu": null, "href": "/catalog/women" },
                { "value": "Sweaters/Knits", "tag": "a", "subMenu": null, "href": "/catalog/women" },
                { "value": "Jackets/Coats", "tag": "a", "subMenu": null, "href": "/catalog/women" },
                { "value": "Blazers", "tag": "a", "subMenu": null, "href": "/catalog/women" },
                { "value": "Denim", "tag": "a", "subMenu": null, "href": "/catalog/women" },
                { "value": "Leggings/Pants", "tag": "a", "subMenu": null, "href": "/catalog/women" },
                { "value": "Skirts/Shorts", "tag": "a", "subMenu": null, "href": "/catalog/women" },
                { "value": "Accessories", "tag": "a", "subMenu": null, "href": "/catalog/women" }
            ],
            [
                { "value": "women", "tag": "h3", "subMenu": null, "href": "/catalog/women" },
                { "value": "Dresses", "tag": "a", "subMenu": null, "href": "/catalog/women" },
                { "value": "Tops", "tag": "a", "subMenu": null, "href": "/catalog/women" },
                { "value": "Sweaters/Knits", "tag": "a", "subMenu": null, "href": "/catalog/women" },
                { "value": "Jackets/Coats", "tag": "a", "subMenu": null, "href": "/catalog/women" },
                { "value": "women", "tag": "h3", "subMenu": null, "href": "/catalog/women" },
                { "value": "Dresses", "tag": "a", "subMenu": null, "href": "/catalog/women" },
                { "value": "Tops", "tag": "a", "subMenu": null, "href": "/catalog/women" },
                { "value": "Sweaters/Knits", "tag": "a", "subMenu": null, "href": "/catalog/women" }
            ],
            [
                { "value": "women", "tag": "h3", "subMenu": null, "href": "/catalog/women" },
                { "value": "Dresses", "tag": "a", "subMenu": null, "href": "/catalog/women" },
                { "value": "Tops", "tag": "a", "subMenu": null, "href": "/catalog/women" },
                { "value": "Sweaters/Knits", "tag": "a", "subMenu": null, "href": "/catalog/women" },
                { "value": "Jackets/Coats", "tag": "a", "subMenu": null, "href": "/catalog/women" },
                { "value": "Super <br> sale!", "tag": "div", "subMenu": null, "href": "#" }
            ]
        ],
        "href": "/catalog/featured"
    },
    {
        "value": "Hot Deals",
        "tag": "a",
        "subMenu": [
            [
                { "value": "women", "tag": "h3", "subMenu": null, "href": "/catalog/women" },
                { "value": "Dresses", "tag": "a", "subMenu": null, "href": "/catalog/women" },
                { "value": "Tops", "tag": "a", "subMenu": null, "href": "/catalog/women" },
                { "value": "Sweaters/Knits", "tag": "a", "subMenu": null, "href": "/catalog/women" },
                { "value": "Jackets/Coats", "tag": "a", "subMenu": null, "href": "/catalog/women" },
                { "value": "Blazers", "tag": "a", "subMenu": null, "href": "/catalog/women" },
                { "value": "Denim", "tag": "a", "subMenu": null, "href": "/catalog/women" },
                { "value": "Leggings/Pants", "tag": "a", "subMenu": null, "href": "/catalog/women" },
                { "value": "Skirts/Shorts", "tag": "a", "subMenu": null, "href": "/catalog/women" },
                { "value": "Accessories", "tag": "a", "subMenu": null, "href": "/catalog/women" }
            ],
            [
                { "value": "women", "tag": "h3", "subMenu": null, "href": "/catalog/women" },
                { "value": "Dresses", "tag": "a", "subMenu": null, "href": "/catalog/women" },
                { "value": "Tops", "tag": "a", "subMenu": null, "href": "/catalog/women" },
                { "value": "Sweaters/Knits", "tag": "a", "subMenu": null, "href": "/catalog/women" },
                { "value": "Jackets/Coats", "tag": "a", "subMenu": null, "href": "/catalog/women" },
                { "value": "women", "tag": "h3", "subMenu": null, "href": "/catalog/women" },
                { "value": "Dresses", "tag": "a", "subMenu": null, "href": "/catalog/women" },
                { "value": "Tops", "tag": "a", "subMenu": null, "href": "/catalog/women" },
                { "value": "Sweaters/Knits", "tag": "a", "subMenu": null, "href": "/catalog/women" }
            ],
            [
                { "value": "women", "tag": "h3", "subMenu": null, "href": "/catalog/women" },
                { "value": "Dresses", "tag": "a", "subMenu": null, "href": "/catalog/women" },
                { "value": "Tops", "tag": "a", "subMenu": null, "href": "/catalog/women" },
                { "value": "Sweaters/Knits", "tag": "a", "subMenu": null, "href": "/catalog/women" },
                { "value": "Jackets/Coats", "tag": "a", "subMenu": null, "href": "/catalog/women" },
                { "value": "Super <br> sale!", "tag": "div", "subMenu": null, "href": "#" }
            ]
        ],
        "href": "/catalog/hot-deals"
    }
]
